constrained_attacks/__init__.py
constrained_attacks/attacks/__init__.py
constrained_attacks/attacks/cpgd/__init__.py
constrained_attacks/attacks/cpgd/cpgd.py
constrained_attacks/attacks/cpgd/tf2_classifier.py
constrained_attacks/attacks/moeva/__init__.py
constrained_attacks/attacks/moeva/adversarial_problem.py
constrained_attacks/attacks/moeva/history_callback.py
constrained_attacks/attacks/moeva/moeva.py
constrained_attacks/attacks/moeva/operators.py
constrained_attacks/classifier/classifier.py
constrained_attacks/classifier/tensorflow_classifier.py
constrained_attacks/constraints/__init__.py
constrained_attacks/constraints/constraints.py
constrained_attacks/constraints/constraints_checker.py
constrained_attacks/constraints/constraints_executor.py
constrained_attacks/constraints/constraints_fixer.py
constrained_attacks/constraints/relation_constraint.py
constrained_attacks/objective_calculator/__init__.py
constrained_attacks/objective_calculator/cache_objective_calculator.py
constrained_attacks/objective_calculator/objective_calculator.py
constrained_attacks/utils/__init__.py
constrained_attacks-0.1.1.dist-info/LICENSE
constrained_attacks-0.1.1.dist-info/WHEEL
constrained_attacks-0.1.1.dist-info/METADATA
constrained_attacks-0.1.1.dist-info/RECORD
